simforge_template/__init__.py
simforge_template/articulation/__init__.py
simforge_template/geometry/__init__.py
simforge_template/image/__init__.py
simforge_template/material/__init__.py
simforge_template/model/__init__.py
simforge_template-0.0.0.dist-info/METADATA
simforge_template-0.0.0.dist-info/WHEEL
simforge_template-0.0.0.dist-info/licenses/LICENSE-CC0
simforge_template-0.0.0.dist-info/RECORD
