Metadata-Version: 2.4
Name: simforge_template
Version: 0.0.0
Summary: SimForge assets
Project-URL: Repository, https://github.com/AndrejOrsula/simforge_template
Author-email: Andrej Orsula <orsula.andrej@gmail.com>
Maintainer-email: Andrej Orsula <orsula.andrej@gmail.com>
License: CC0-1.0
License-File: LICENSE-CC0
Keywords: procedural,simulation
Classifier: License :: CC0 1.0 Universal (CC0 1.0) Public Domain Dedication
Classifier: Programming Language :: Python
Classifier: Topic :: Games/Entertainment :: Simulation
Classifier: Topic :: Multimedia :: Graphics :: 3D Modeling
Requires-Python: >=3.10
Requires-Dist: pytest-cov>=6.0.0
Requires-Dist: simforge[all]
